{
    "title": "새로나온책",
    "link": "http://book.interpark.com",
    "language": "ko",
    "copyright": "Copyright ⓒ 2009 INTERPARK INT All rights reserved.",
    "pubDate": "10 Jan 2023 22:30:10 GMT",
    "imageUrl": "http://bimage.interpark.com/renewPark/topGnb/logo.jpg",
    "totalResults": 30,
    "startIndex": 1,
    "itemsPerPage": 30,
    "maxResults": 30,
    "queryType": "",
    "searchCategoryId": "300",
    "searchCategoryName": "음반",
    "returnCode": "000",
    "returnMessage": "정상",
    "item": [
        {
            "itemId": 356223937,
            "title": "몬스타엑스(MONSTA X) - REASON[Jewel ver.][MINHYUK ver. + KIHYUN ver. + HYUNGWON ver. + JOOHONEY ver. + I.M ver.][5SET]",
            "description": "",
            "pubDate": "20230110",
            "priceStandard": 69000,
            "priceSales": 55000,
            "discountRate": "20",
            "saleStatus": "일시품절",
            "mileage": "550",
            "mileageRate": "1",
            "coverSmallUrl": "http://bimage.interpark.com/goods_image/3/9/3/7/356223937h.jpg",
            "coverLargeUrl": "http://bimage.interpark.com/goods_image/3/9/3/7/356223937s.jpg",
            "categoryId": "301",
            "categoryName": "음반",
            "publisher": "Kakao Entertainment",
            "customerReviewRank": 0,
            "author": "몬스타엑스(Monsta X) ",
            "translator": "",
            "isbn": "L100005890",
            "link": "http://book.interpark.com/blog/integration/product/itemDetail.rdo?prdNo=356223937&refererType=8304",
            "mobileLink": "http://m.book.interpark.com/view.html?PRD_NO=356223937&SHOP_NO=0000500000&SUB_CATE=2004",
            "additionalLink": "http://book.interpark.com/gate/ippgw.jsp?goods_no=356223937&biz_cd=",
            "reviewCount": 0
        },
        {
            "itemId": 356111734,
            "title": "Jamie Lee Curtis/Will Patton - 할로윈 엔드 (Halloween Ends) (2022)(지역코드1)(한글무자막)(DVD) - DVD",
            "description": "",
            "pubDate": "20230110",
            "priceStandard": 54000,
            "priceSales": 54000,
            "discountRate": "0",
            "saleStatus": "판매중",
            "mileage": "540",
            "mileageRate": "1",
            "coverSmallUrl": "http://bimage.interpark.com/2004/images/adult_80.gif",
            "coverLargeUrl": "http://bimage.interpark.com/2004/images/adult_80.gif",
            "categoryName": "",
            "publisher": "",
            "customerReviewRank": 0,
            "author": "",
            "translator": "",
            "isbn": "0191329237540",
            "link": "http://book.interpark.com/blog/integration/product/itemDetail.rdo?prdNo=356111734&refererType=8304",
            "mobileLink": "http://m.book.interpark.com/view.html?PRD_NO=356111734&SHOP_NO=0000500000&SUB_CATE=2004",
            "additionalLink": "http://book.interpark.com/gate/ippgw.jsp?goods_no=356111734&biz_cd=",
            "reviewCount": 0
        },
        {
            "itemId": 356111733,
            "title": "Paul Newman/Jessica Tandy - Nobody&#39s Fool (Special Edition) (노스바스의 추억) (1994)(한글무자막)(4K Ultra HD + Blu-ray) - 블루레이",
            "description": "",
            "pubDate": "20230110",
            "priceStandard": 65500,
            "priceSales": 65500,
            "discountRate": "0",
            "saleStatus": "일시품절",
            "mileage": "660",
            "mileageRate": "1",
            "coverSmallUrl": "http://bimage.interpark.com/2004/images/adult_80.gif",
            "coverLargeUrl": "http://bimage.interpark.com/2004/images/adult_80.gif",
            "categoryName": "",
            "publisher": "",
            "customerReviewRank": 0,
            "author": "",
            "translator": "",
            "isbn": "0738329261337",
            "link": "http://book.interpark.com/blog/integration/product/itemDetail.rdo?prdNo=356111733&refererType=8304",
            "mobileLink": "http://m.book.interpark.com/view.html?PRD_NO=356111733&SHOP_NO=0000500000&SUB_CATE=2004",
            "additionalLink": "http://book.interpark.com/gate/ippgw.jsp?goods_no=356111733&biz_cd=",
            "reviewCount": 0
        },
        {
            "itemId": 356111664,
            "title": "Jamie Lee Curtis - 할로윈 트릴로지 (Halloween Trilogy) (지역코드1)(한글무자막)(DVD) - DVD",
            "description": "",
            "pubDate": "20230110",
            "priceStandard": 85700,
            "priceSales": 85700,
            "discountRate": "0",
            "saleStatus": "판매중",
            "mileage": "860",
            "mileageRate": "1",
            "coverSmallUrl": "http://bimage.interpark.com/2004/images/adult_80.gif",
            "coverLargeUrl": "http://bimage.interpark.com/2004/images/adult_80.gif",
            "categoryName": "",
            "publisher": "",
            "customerReviewRank": 0,
            "author": "",
            "translator": "",
            "isbn": "0191329237960",
            "link": "http://book.interpark.com/blog/integration/product/itemDetail.rdo?prdNo=356111664&refererType=8304",
            "mobileLink": "http://m.book.interpark.com/view.html?PRD_NO=356111664&SHOP_NO=0000500000&SUB_CATE=2004",
            "additionalLink": "http://book.interpark.com/gate/ippgw.jsp?goods_no=356111664&biz_cd=",
            "reviewCount": 0
        },
        {
            "itemId": 356111721,
            "title": "Jamie Lee Curtis - 할로윈 트릴로지 (Halloween Trilogy) (한글무자막) - 블루레이",
            "description": "",
            "pubDate": "20230110",
            "priceStandard": 115000,
            "priceSales": 115000,
            "discountRate": "0",
            "saleStatus": "판매중",
            "mileage": "1150",
            "mileageRate": "1",
            "coverSmallUrl": "http://bimage.interpark.com/2004/images/adult_80.gif",
            "coverLargeUrl": "http://bimage.interpark.com/2004/images/adult_80.gif",
            "categoryName": "",
            "publisher": "",
            "customerReviewRank": 0,
            "author": "",
            "translator": "",
            "isbn": "0191329237977",
            "link": "http://book.interpark.com/blog/integration/product/itemDetail.rdo?prdNo=356111721&refererType=8304",
            "mobileLink": "http://m.book.interpark.com/view.html?PRD_NO=356111721&SHOP_NO=0000500000&SUB_CATE=2004",
            "additionalLink": "http://book.interpark.com/gate/ippgw.jsp?goods_no=356111721&biz_cd=",
            "reviewCount": 0
        },
        {
            "itemId": 355889373,
            "title": "Samantha Scaffidi - 테리파이어 2 (Terrifier 2) (한글무자막) - 블루레이",
            "description": "",
            "pubDate": "20230110",
            "priceStandard": 48500,
            "priceSales": 48500,
            "discountRate": "0",
            "saleStatus": "판매중",
            "mileage": "490",
            "mileageRate": "1",
            "coverSmallUrl": "http://bimage.interpark.com/2004/images/adult_80.gif",
            "coverLargeUrl": "http://bimage.interpark.com/2004/images/adult_80.gif",
            "categoryName": "",
            "publisher": "",
            "customerReviewRank": 0,
            "author": "",
            "translator": "",
            "isbn": "0767685168233",
            "link": "http://book.interpark.com/blog/integration/product/itemDetail.rdo?prdNo=355889373&refererType=8304",
            "mobileLink": "http://m.book.interpark.com/view.html?PRD_NO=355889373&SHOP_NO=0000500000&SUB_CATE=2004",
            "additionalLink": "http://book.interpark.com/gate/ippgw.jsp?goods_no=355889373&biz_cd=",
            "reviewCount": 0
        },
        {
            "itemId": 355979566,
            "title": "Jamie Lee Curtis - (Halloween Ends) 할로윈 엔드 (한글무자막)(Blu-ray+DVD) - 블루레이",
            "description": "",
            "pubDate": "20230110",
            "priceStandard": 68100,
            "priceSales": 68100,
            "discountRate": "0",
            "saleStatus": "판매중",
            "mileage": "690",
            "mileageRate": "1",
            "coverSmallUrl": "http://bimage.interpark.com/2004/images/adult_80.gif",
            "coverLargeUrl": "http://bimage.interpark.com/2004/images/adult_80.gif",
            "categoryName": "",
            "publisher": "",
            "customerReviewRank": 0,
            "author": "",
            "translator": "",
            "isbn": "0191329237557",
            "link": "http://book.interpark.com/blog/integration/product/itemDetail.rdo?prdNo=355979566&refererType=8304",
            "mobileLink": "http://m.book.interpark.com/view.html?PRD_NO=355979566&SHOP_NO=0000500000&SUB_CATE=2004",
            "additionalLink": "http://book.interpark.com/gate/ippgw.jsp?goods_no=355979566&biz_cd=",
            "reviewCount": 0
        },
        {
            "itemId": 356111735,
            "title": "Jamie Lee Curtis/Will Patton - 할로윈 엔드 (Halloween Ends) (2022)(한글무자막)(4K Ultra HD + Blu-ray) - 블루레이",
            "description": "",
            "pubDate": "20230110",
            "priceStandard": 82100,
            "priceSales": 82100,
            "discountRate": "0",
            "saleStatus": "판매중",
            "mileage": "830",
            "mileageRate": "1",
            "coverSmallUrl": "http://bimage.interpark.com/2004/images/adult_80.gif",
            "coverLargeUrl": "http://bimage.interpark.com/2004/images/adult_80.gif",
            "categoryName": "",
            "publisher": "",
            "customerReviewRank": 0,
            "author": "",
            "translator": "",
            "isbn": "0191329237564",
            "link": "http://book.interpark.com/blog/integration/product/itemDetail.rdo?prdNo=356111735&refererType=8304",
            "mobileLink": "http://m.book.interpark.com/view.html?PRD_NO=356111735&SHOP_NO=0000500000&SUB_CATE=2004",
            "additionalLink": "http://book.interpark.com/gate/ippgw.jsp?goods_no=356111735&biz_cd=",
            "reviewCount": 0
        },
        {
            "itemId": 356423719,
            "title": "위하준/진기주 - 미드나이트 (Midnight) (한국영화)(한글무자막) - 블루레이",
            "description": "",
            "pubDate": "20230110",
            "priceStandard": 33000,
            "priceSales": 33000,
            "discountRate": "0",
            "saleStatus": "판매중",
            "mileage": "330",
            "mileageRate": "1",
            "coverSmallUrl": "http://bimage.interpark.com/goods_image/3/7/1/9/356423719h.jpg",
            "coverLargeUrl": "http://bimage.interpark.com/goods_image/3/7/1/9/356423719s.jpg",
            "categoryName": "",
            "publisher": "",
            "customerReviewRank": 0,
            "author": "",
            "translator": "",
            "isbn": "05060000704549",
            "link": "http://book.interpark.com/blog/integration/product/itemDetail.rdo?prdNo=356423719&refererType=8304",
            "mobileLink": "http://m.book.interpark.com/view.html?PRD_NO=356423719&SHOP_NO=0000500000&SUB_CATE=2004",
            "additionalLink": "http://book.interpark.com/gate/ippgw.jsp?goods_no=356423719&biz_cd=",
            "reviewCount": 0
        },
        {
            "itemId": 356423727,
            "title": "최민식 - 올드보이 (Oldboy) (한국영화)(한글무자막) - 블루레이",
            "description": "",
            "pubDate": "20230110",
            "priceStandard": 38900,
            "priceSales": 38900,
            "discountRate": "0",
            "saleStatus": "판매중",
            "mileage": "390",
            "mileageRate": "1",
            "coverSmallUrl": "http://bimage.interpark.com/2004/images/adult_80.gif",
            "coverLargeUrl": "http://bimage.interpark.com/2004/images/adult_80.gif",
            "categoryName": "",
            "publisher": "",
            "customerReviewRank": 0,
            "author": "",
            "translator": "",
            "isbn": "05027035020914",
            "link": "http://book.interpark.com/blog/integration/product/itemDetail.rdo?prdNo=356423727&refererType=8304",
            "mobileLink": "http://m.book.interpark.com/view.html?PRD_NO=356423727&SHOP_NO=0000500000&SUB_CATE=2004",
            "additionalLink": "http://book.interpark.com/gate/ippgw.jsp?goods_no=356423727&biz_cd=",
            "reviewCount": 0
        },
        {
            "itemId": 356423723,
            "title": "최민식 - 올드보이 (Oldboy) (한국영화)(한글무자막)(DVD) - DVD",
            "description": "",
            "pubDate": "20230110",
            "priceStandard": 23000,
            "priceSales": 23000,
            "discountRate": "0",
            "saleStatus": "판매중",
            "mileage": "230",
            "mileageRate": "1",
            "coverSmallUrl": "http://bimage.interpark.com/2004/images/adult_80.gif",
            "coverLargeUrl": "http://bimage.interpark.com/2004/images/adult_80.gif",
            "categoryName": "",
            "publisher": "",
            "customerReviewRank": 0,
            "author": "",
            "translator": "",
            "isbn": "05027035020921",
            "link": "http://book.interpark.com/blog/integration/product/itemDetail.rdo?prdNo=356423723&refererType=8304",
            "mobileLink": "http://m.book.interpark.com/view.html?PRD_NO=356423723&SHOP_NO=0000500000&SUB_CATE=2004",
            "additionalLink": "http://book.interpark.com/gate/ippgw.jsp?goods_no=356423723&biz_cd=",
            "reviewCount": 0
        },
        {
            "itemId": 356423722,
            "title": "임수정 - 장화, 홍련 (A Tale of Two Sisters) (한국영화)(한글무자막) - 블루레이",
            "description": "",
            "pubDate": "20230110",
            "priceStandard": 38900,
            "priceSales": 38900,
            "discountRate": "0",
            "saleStatus": "판매중",
            "mileage": "390",
            "mileageRate": "1",
            "coverSmallUrl": "http://bimage.interpark.com/goods_image/3/7/2/2/356423722h.jpg",
            "coverLargeUrl": "http://bimage.interpark.com/goods_image/3/7/2/2/356423722s.jpg",
            "categoryName": "",
            "publisher": "",
            "customerReviewRank": 0,
            "author": "",
            "translator": "",
            "isbn": "05027035023410",
            "link": "http://book.interpark.com/blog/integration/product/itemDetail.rdo?prdNo=356423722&refererType=8304",
            "mobileLink": "http://m.book.interpark.com/view.html?PRD_NO=356423722&SHOP_NO=0000500000&SUB_CATE=2004",
            "additionalLink": "http://book.interpark.com/gate/ippgw.jsp?goods_no=356423722&biz_cd=",
            "reviewCount": 0
        },
        {
            "itemId": 356424363,
            "title": "유아인/전종서 - 버닝 (Burning) (한국영화)(한글무자막) - 블루레이",
            "description": "",
            "pubDate": "20230110",
            "priceStandard": 38900,
            "priceSales": 38900,
            "discountRate": "0",
            "saleStatus": "판매중",
            "mileage": "390",
            "mileageRate": "1",
            "coverSmallUrl": "http://bimage.interpark.com/2004/images/adult_80.gif",
            "coverLargeUrl": "http://bimage.interpark.com/2004/images/adult_80.gif",
            "categoryName": "",
            "publisher": "",
            "customerReviewRank": 0,
            "author": "",
            "translator": "",
            "isbn": "05060238033145",
            "link": "http://book.interpark.com/blog/integration/product/itemDetail.rdo?prdNo=356424363&refererType=8304",
            "mobileLink": "http://m.book.interpark.com/view.html?PRD_NO=356424363&SHOP_NO=0000500000&SUB_CATE=2004",
            "additionalLink": "http://book.interpark.com/gate/ippgw.jsp?goods_no=356424363&biz_cd=",
            "reviewCount": 0
        },
        {
            "itemId": 356424364,
            "title": "유아인/전종서 - 버닝 (Burning) (한국영화)(한글무자막)(DVD) - DVD",
            "description": "",
            "pubDate": "20230110",
            "priceStandard": 23000,
            "priceSales": 23000,
            "discountRate": "0",
            "saleStatus": "판매중",
            "mileage": "230",
            "mileageRate": "1",
            "coverSmallUrl": "http://bimage.interpark.com/2004/images/adult_80.gif",
            "coverLargeUrl": "http://bimage.interpark.com/2004/images/adult_80.gif",
            "categoryName": "",
            "publisher": "",
            "customerReviewRank": 0,
            "author": "",
            "translator": "",
            "isbn": "05060238033022",
            "link": "http://book.interpark.com/blog/integration/product/itemDetail.rdo?prdNo=356424364&refererType=8304",
            "mobileLink": "http://m.book.interpark.com/view.html?PRD_NO=356424364&SHOP_NO=0000500000&SUB_CATE=2004",
            "additionalLink": "http://book.interpark.com/gate/ippgw.jsp?goods_no=356424364&biz_cd=",
            "reviewCount": 0
        },
        {
            "itemId": 356423731,
            "title": "송강호/최민식/이영애 - 복수 3부작 (Vengeance Trilogy) : Sympathy for Mr. Vengeance (복수는 나의 것) / Oldboy (올드보이) / Lady Vengeance (친절한 금자씨) (한국영화)(한글무자막) - 블루레이",
            "description": "",
            "pubDate": "20230110",
            "priceStandard": 70600,
            "priceSales": 70600,
            "discountRate": "0",
            "saleStatus": "판매중",
            "mileage": "710",
            "mileageRate": "1",
            "coverSmallUrl": "http://bimage.interpark.com/2004/images/adult_80.gif",
            "coverLargeUrl": "http://bimage.interpark.com/2004/images/adult_80.gif",
            "categoryName": "",
            "publisher": "",
            "customerReviewRank": 0,
            "author": "",
            "translator": "",
            "isbn": "05027035021393",
            "link": "http://book.interpark.com/blog/integration/product/itemDetail.rdo?prdNo=356423731&refererType=8304",
            "mobileLink": "http://m.book.interpark.com/view.html?PRD_NO=356423731&SHOP_NO=0000500000&SUB_CATE=2004",
            "additionalLink": "http://book.interpark.com/gate/ippgw.jsp?goods_no=356423731&biz_cd=",
            "reviewCount": 0
        },
        {
            "itemId": 356424370,
            "title": "이정재/최민식/황정민 - 신세계 (New World) (한국영화)(한글무자막) - 블루레이",
            "description": "",
            "pubDate": "20230110",
            "priceStandard": 23000,
            "priceSales": 23000,
            "discountRate": "0",
            "saleStatus": "판매중",
            "mileage": "230",
            "mileageRate": "1",
            "coverSmallUrl": "http://bimage.interpark.com/2004/images/adult_80.gif",
            "coverLargeUrl": "http://bimage.interpark.com/2004/images/adult_80.gif",
            "categoryName": "",
            "publisher": "",
            "customerReviewRank": 0,
            "author": "",
            "translator": "",
            "isbn": "05060000702842",
            "link": "http://book.interpark.com/blog/integration/product/itemDetail.rdo?prdNo=356424370&refererType=8304",
            "mobileLink": "http://m.book.interpark.com/view.html?PRD_NO=356424370&SHOP_NO=0000500000&SUB_CATE=2004",
            "additionalLink": "http://book.interpark.com/gate/ippgw.jsp?goods_no=356424370&biz_cd=",
            "reviewCount": 0
        },
        {
            "itemId": 356223934,
            "title": "몬스타엑스(MONSTA X) -  REASON [12th Mini Album][VER.1 + VER.2 + VER.3 + VER.4][4SET]",
            "description": "",
            "pubDate": "20230110",
            "priceStandard": 88000,
            "priceSales": 71200,
            "discountRate": "19",
            "saleStatus": "일시품절",
            "mileage": "720",
            "mileageRate": "1",
            "coverSmallUrl": "http://bimage.interpark.com/goods_image/3/9/3/4/356223934h.jpg",
            "coverLargeUrl": "http://bimage.interpark.com/goods_image/3/9/3/4/356223934s.jpg",
            "categoryId": "301",
            "categoryName": "음반",
            "publisher": "Kakao Entertainment",
            "customerReviewRank": 0,
            "author": "몬스타엑스(Monsta X) ",
            "translator": "",
            "isbn": "L100005889",
            "link": "http://book.interpark.com/blog/integration/product/itemDetail.rdo?prdNo=356223934&refererType=8304",
            "mobileLink": "http://m.book.interpark.com/view.html?PRD_NO=356223934&SHOP_NO=0000500000&SUB_CATE=2004",
            "additionalLink": "http://book.interpark.com/gate/ippgw.jsp?goods_no=356223934&biz_cd=",
            "reviewCount": 0
        },
        {
            "itemId": 356223935,
            "title": "몬스타엑스(MONSTA X) -  REASON [12th Mini Album][Cassette Tape Ver.]",
            "description": "",
            "pubDate": "20230110",
            "priceStandard": 16500,
            "priceSales": 13400,
            "discountRate": "19",
            "saleStatus": "일시품절",
            "mileage": "140",
            "mileageRate": "1",
            "coverSmallUrl": "http://bimage.interpark.com/goods_image/3/9/3/5/356223935h.jpg",
            "coverLargeUrl": "http://bimage.interpark.com/goods_image/3/9/3/5/356223935s.jpg",
            "categoryId": "301",
            "categoryName": "음반",
            "publisher": "Kakao Entertainment",
            "customerReviewRank": 0,
            "author": "몬스타엑스(Monsta X) ",
            "translator": "",
            "isbn": "L200002569",
            "link": "http://book.interpark.com/blog/integration/product/itemDetail.rdo?prdNo=356223935&refererType=8304",
            "mobileLink": "http://m.book.interpark.com/view.html?PRD_NO=356223935&SHOP_NO=0000500000&SUB_CATE=2004",
            "additionalLink": "http://book.interpark.com/gate/ippgw.jsp?goods_no=356223935&biz_cd=",
            "reviewCount": 0
        },
        {
            "itemId": 356223936,
            "title": "몬스타엑스(MONSTA X) -  REASON [12th Mini Album][KiT Ver.]",
            "description": "",
            "pubDate": "20230110",
            "priceStandard": 27000,
            "priceSales": 21800,
            "discountRate": "19",
            "saleStatus": "일시품절",
            "mileage": "220",
            "mileageRate": "1",
            "coverSmallUrl": "http://bimage.interpark.com/goods_image/3/9/3/6/356223936h.jpg",
            "coverLargeUrl": "http://bimage.interpark.com/goods_image/3/9/3/6/356223936s.jpg",
            "categoryId": "301",
            "categoryName": "음반",
            "publisher": "Kakao Entertainment",
            "customerReviewRank": 0,
            "author": "몬스타엑스(Monsta X) ",
            "translator": "",
            "isbn": "L100005891",
            "link": "http://book.interpark.com/blog/integration/product/itemDetail.rdo?prdNo=356223936&refererType=8304",
            "mobileLink": "http://m.book.interpark.com/view.html?PRD_NO=356223936&SHOP_NO=0000500000&SUB_CATE=2004",
            "additionalLink": "http://book.interpark.com/gate/ippgw.jsp?goods_no=356223936&biz_cd=",
            "reviewCount": 0
        },
        {
            "itemId": 356223938,
            "title": "몬스타엑스(MONSTA X) - REASON[Jewel ver.][MINHYUK ver. or KIHYUN ver. or HYUNGWON ver. or JOOHONEY ver. or I.M ver.][랜덤 1종 발송]",
            "description": "",
            "pubDate": "20230110",
            "priceStandard": 13800,
            "priceSales": 11100,
            "discountRate": "20",
            "saleStatus": "판매중",
            "mileage": "120",
            "mileageRate": "1",
            "coverSmallUrl": "http://bimage.interpark.com/goods_image/3/9/3/8/356223938h.jpg",
            "coverLargeUrl": "http://bimage.interpark.com/goods_image/3/9/3/8/356223938s.jpg",
            "categoryId": "301",
            "categoryName": "음반",
            "publisher": "Kakao Entertainment",
            "customerReviewRank": 0,
            "author": "몬스타엑스(Monsta X) ",
            "translator": "",
            "isbn": "L100005890",
            "link": "http://book.interpark.com/blog/integration/product/itemDetail.rdo?prdNo=356223938&refererType=8304",
            "mobileLink": "http://m.book.interpark.com/view.html?PRD_NO=356223938&SHOP_NO=0000500000&SUB_CATE=2004",
            "additionalLink": "http://book.interpark.com/gate/ippgw.jsp?goods_no=356223938&biz_cd=",
            "reviewCount": 0
        },
        {
            "itemId": 356305388,
            "title": "오느린윤혜린 1집 - Be opposite",
            "description": "",
            "pubDate": "20230109",
            "priceStandard": 20200,
            "priceSales": 16300,
            "discountRate": "19",
            "saleStatus": "판매중",
            "mileage": "170",
            "mileageRate": "1",
            "coverSmallUrl": "http://bimage.interpark.com/goods_image/5/3/8/8/356305388h.jpg",
            "coverLargeUrl": "http://bimage.interpark.com/goods_image/5/3/8/8/356305388s.jpg",
            "categoryId": "301",
            "categoryName": "음반",
            "publisher": "비스킷 사운드",
            "customerReviewRank": 0,
            "author": "오느린윤혜린",
            "translator": "",
            "isbn": "WB2672K",
            "link": "http://book.interpark.com/blog/integration/product/itemDetail.rdo?prdNo=356305388&refererType=8304",
            "mobileLink": "http://m.book.interpark.com/view.html?PRD_NO=356305388&SHOP_NO=0000500000&SUB_CATE=2004",
            "additionalLink": "http://book.interpark.com/gate/ippgw.jsp?goods_no=356305388&biz_cd=",
            "reviewCount": 0
        },
        {
            "itemId": 355919546,
            "title": "세븐틴(Seventeen) - 2022 SVT PHOTOBOOK THE NAME;17",
            "description": "",
            "pubDate": "20230109",
            "priceStandard": 40000,
            "priceSales": 40000,
            "discountRate": "0",
            "saleStatus": "일시품절",
            "mileage": "400",
            "mileageRate": "1",
            "coverSmallUrl": "http://bimage.interpark.com/goods_image/9/5/4/6/355919546h.jpg",
            "coverLargeUrl": "http://bimage.interpark.com/goods_image/9/5/4/6/355919546s.jpg",
            "categoryId": "301",
            "categoryName": "음반",
            "publisher": "HYBE(하이브)",
            "customerReviewRank": 0,
            "author": "세븐틴(Seventeen)",
            "translator": "",
            "link": "http://book.interpark.com/blog/integration/product/itemDetail.rdo?prdNo=355919546&refererType=8304",
            "mobileLink": "http://m.book.interpark.com/view.html?PRD_NO=355919546&SHOP_NO=0000500000&SUB_CATE=2004",
            "additionalLink": "http://book.interpark.com/gate/ippgw.jsp?goods_no=355919546&biz_cd=",
            "reviewCount": 0
        },
        {
            "itemId": 356154951,
            "title": "에이티비오(ATBO) - 2023 SEASON’S GREETINGS ",
            "description": "",
            "pubDate": "20230109",
            "priceStandard": 40000,
            "priceSales": 40000,
            "discountRate": "0",
            "saleStatus": "판매중",
            "mileage": "0",
            "mileageRate": "0",
            "coverSmallUrl": "http://bimage.interpark.com/goods_image/4/9/5/1/356154951h.jpg",
            "coverLargeUrl": "http://bimage.interpark.com/goods_image/4/9/5/1/356154951s.jpg",
            "categoryId": "314",
            "categoryName": "음반",
            "publisher": "(주)애플뮤직",
            "customerReviewRank": 0,
            "author": "ATBO(에이티비오)",
            "translator": "",
            "isbn": "APMS057",
            "link": "http://book.interpark.com/blog/integration/product/itemDetail.rdo?prdNo=356154951&refererType=8304",
            "mobileLink": "http://m.book.interpark.com/view.html?PRD_NO=356154951&SHOP_NO=0000500000&SUB_CATE=2004",
            "additionalLink": "http://book.interpark.com/gate/ippgw.jsp?goods_no=356154951&biz_cd=",
            "reviewCount": 0
        },
        {
            "itemId": 356154952,
            "title": "위클리(Weekly) - 2023 SEASON’S GREETINGS ",
            "description": "",
            "pubDate": "20230109",
            "priceStandard": 40000,
            "priceSales": 40000,
            "discountRate": "0",
            "saleStatus": "판매중",
            "mileage": "0",
            "mileageRate": "0",
            "coverSmallUrl": "http://bimage.interpark.com/goods_image/4/9/5/2/356154952h.jpg",
            "coverLargeUrl": "http://bimage.interpark.com/goods_image/4/9/5/2/356154952s.jpg",
            "categoryId": "314",
            "categoryName": "음반",
            "publisher": "(주)애플뮤직",
            "customerReviewRank": 0,
            "author": "위클리(Weeekly)",
            "translator": "",
            "isbn": "APMS056",
            "link": "http://book.interpark.com/blog/integration/product/itemDetail.rdo?prdNo=356154952&refererType=8304",
            "mobileLink": "http://m.book.interpark.com/view.html?PRD_NO=356154952&SHOP_NO=0000500000&SUB_CATE=2004",
            "additionalLink": "http://book.interpark.com/gate/ippgw.jsp?goods_no=356154952&biz_cd=",
            "reviewCount": 0
        },
        {
            "itemId": 356354510,
            "title": "Cryptworm - Spewing Mephitic Putridity (Cassette Tape)",
            "description": "",
            "pubDate": "20230106",
            "priceStandard": 24800,
            "priceSales": 24800,
            "discountRate": "0",
            "saleStatus": "판매중",
            "mileage": "250",
            "mileageRate": "1",
            "coverSmallUrl": "http://bimage.interpark.com/goods_image/4/5/1/0/356354510h.jpg",
            "coverLargeUrl": "http://bimage.interpark.com/goods_image/4/5/1/0/356354510s.jpg",
            "categoryId": "319",
            "categoryName": "음반",
            "publisher": "",
            "customerReviewRank": 0,
            "author": "Cryptworm",
            "translator": "",
            "isbn": "I1439839",
            "link": "http://book.interpark.com/blog/integration/product/itemDetail.rdo?prdNo=356354510&refererType=8304",
            "mobileLink": "http://m.book.interpark.com/view.html?PRD_NO=356354510&SHOP_NO=0000500000&SUB_CATE=2004",
            "additionalLink": "http://book.interpark.com/gate/ippgw.jsp?goods_no=356354510&biz_cd=",
            "reviewCount": 0
        },
        {
            "itemId": 356354548,
            "title": "Floating Points - 2022 (LP)",
            "description": "",
            "pubDate": "20230106",
            "priceStandard": 44300,
            "priceSales": 44300,
            "discountRate": "0",
            "saleStatus": "판매중",
            "mileage": "450",
            "mileageRate": "1",
            "coverSmallUrl": "http://bimage.interpark.com/goods_image/4/5/4/8/356354548h.jpg",
            "coverLargeUrl": "http://bimage.interpark.com/goods_image/4/5/4/8/356354548s.jpg",
            "categoryId": "319",
            "categoryName": "음반",
            "publisher": "",
            "customerReviewRank": 0,
            "author": "Floating Points",
            "translator": "",
            "isbn": "I1439893",
            "link": "http://book.interpark.com/blog/integration/product/itemDetail.rdo?prdNo=356354548&refererType=8304",
            "mobileLink": "http://m.book.interpark.com/view.html?PRD_NO=356354548&SHOP_NO=0000500000&SUB_CATE=2004",
            "additionalLink": "http://book.interpark.com/gate/ippgw.jsp?goods_no=356354548&biz_cd=",
            "reviewCount": 0
        },
        {
            "itemId": 356354545,
            "title": "Patricia Kopatchinskaja/Fazil Say - 브람스, 바르톡 & 야나첵: 바이올린 소나타 (Brahms, Bartok & Janacek: Violin Sonatas)(CD)",
            "description": "",
            "pubDate": "20230106",
            "priceStandard": 38800,
            "priceSales": 38800,
            "discountRate": "0",
            "saleStatus": "판매중",
            "mileage": "390",
            "mileageRate": "1",
            "coverSmallUrl": "http://bimage.interpark.com/goods_image/4/5/4/5/356354545h.jpg",
            "coverLargeUrl": "http://bimage.interpark.com/goods_image/4/5/4/5/356354545s.jpg",
            "categoryId": "319",
            "categoryName": "음반",
            "publisher": "",
            "customerReviewRank": 0,
            "author": "Patricia Kopatchinskaja/Fazil Say",
            "translator": "",
            "isbn": "I1439882",
            "link": "http://book.interpark.com/blog/integration/product/itemDetail.rdo?prdNo=356354545&refererType=8304",
            "mobileLink": "http://m.book.interpark.com/view.html?PRD_NO=356354545&SHOP_NO=0000500000&SUB_CATE=2004",
            "additionalLink": "http://book.interpark.com/gate/ippgw.jsp?goods_no=356354545&biz_cd=",
            "reviewCount": 0
        },
        {
            "itemId": 356154943,
            "title": "아론(Aaron) - 2023 SEASON’S GREETINGS [Aaron]",
            "description": "",
            "pubDate": "20230106",
            "priceStandard": 43000,
            "priceSales": 43000,
            "discountRate": "0",
            "saleStatus": "판매중",
            "mileage": "430",
            "mileageRate": "1",
            "coverSmallUrl": "http://bimage.interpark.com/goods_image/4/9/4/3/356154943h.jpg",
            "coverLargeUrl": "http://bimage.interpark.com/goods_image/4/9/4/3/356154943s.jpg",
            "categoryId": "314",
            "categoryName": "음반",
            "publisher": "다날",
            "customerReviewRank": 0,
            "author": "아론(Aaron)",
            "translator": "",
            "isbn": "AF000194",
            "link": "http://book.interpark.com/blog/integration/product/itemDetail.rdo?prdNo=356154943&refererType=8304",
            "mobileLink": "http://m.book.interpark.com/view.html?PRD_NO=356154943&SHOP_NO=0000500000&SUB_CATE=2004",
            "additionalLink": "http://book.interpark.com/gate/ippgw.jsp?goods_no=356154943&biz_cd=",
            "reviewCount": 0
        },
        {
            "itemId": 356079385,
            "title": "저스트비(JUST B) -  2023 Season&#39s Greetings",
            "description": "",
            "pubDate": "20230106",
            "priceStandard": 42000,
            "priceSales": 42000,
            "discountRate": "0",
            "saleStatus": "판매중",
            "mileage": "420",
            "mileageRate": "1",
            "coverSmallUrl": "http://bimage.interpark.com/goods_image/9/3/8/5/356079385h.jpg",
            "coverLargeUrl": "http://bimage.interpark.com/goods_image/9/3/8/5/356079385s.jpg",
            "categoryId": "314",
            "categoryName": "음반",
            "publisher": "FNC엔터테인먼트",
            "customerReviewRank": 0,
            "author": "저스트비(JUST B)",
            "translator": "",
            "link": "http://book.interpark.com/blog/integration/product/itemDetail.rdo?prdNo=356079385&refererType=8304",
            "mobileLink": "http://m.book.interpark.com/view.html?PRD_NO=356079385&SHOP_NO=0000500000&SUB_CATE=2004",
            "additionalLink": "http://book.interpark.com/gate/ippgw.jsp?goods_no=356079385&biz_cd=",
            "reviewCount": 0
        },
        {
            "itemId": 355930214,
            "title": "Flower Kings - Unfold The Future (2CD)",
            "description": "",
            "pubDate": "20230106",
            "priceStandard": 36100,
            "priceSales": 36100,
            "discountRate": "0",
            "saleStatus": "일시품절",
            "mileage": "370",
            "mileageRate": "1",
            "coverSmallUrl": "http://bimage.interpark.com/goods_image/0/2/1/4/355930214h.jpg",
            "coverLargeUrl": "http://bimage.interpark.com/goods_image/0/2/1/4/355930214s.jpg",
            "categoryId": "319",
            "categoryName": "음반",
            "publisher": "",
            "customerReviewRank": 0,
            "author": "Flower Kings",
            "translator": "",
            "isbn": "I1433292",
            "link": "http://book.interpark.com/blog/integration/product/itemDetail.rdo?prdNo=355930214&refererType=8304",
            "mobileLink": "http://m.book.interpark.com/view.html?PRD_NO=355930214&SHOP_NO=0000500000&SUB_CATE=2004",
            "additionalLink": "http://book.interpark.com/gate/ippgw.jsp?goods_no=355930214&biz_cd=",
            "reviewCount": 0
        }
    ]
}